{
  "id": 2038,
  "name": null,
  "ydk": "#created\nby\n...\n#main\n72989439\n39507162\n71413901\n09596126\n70074904\n07572887\n76922029\n74131780\n88240808\n88240808\n26202165\n08131171\n31786629\n31786629\n31786629\n33184167\n14087893\n14087893\n44763025\n79571449\n19613556\n05318639\n71044499\n71044499\n55144522\n70828912\n32807846\n32807846\n45986603\n97077563\n44095762\n63356631\n63356631\n83555666\n41420027\n41420027\n41420027\n53582587\n64697231\n64697231\n#extra\n80071763\n80071763\n80071763\n86805855\n86805855\n86805855\n87751584\n87751584\n87751584\n41462083\n41462083\n41462083\n63519819\n63519819\n63519819\n!side\n65240384\n61831093\n47507260\n88472456\n14087893\n69162969\n15800838\n15800838\n51452091\n51452091\n51452091\n82732705\n82732705\n82732705\n64697231\n",
  "builderName": "thenano5560",
  "builderId": "9SZ3oySHK4WE4wMS67Ucju",
  "deckTypeName": "Chaos Warrior Turbo",
  "category": "Midrange",
  "display": true,
  "formatName": "Goat",
  "formatId": 8,
  "eventId": 294,
  "communityName": "Format Library",
  "eventAbbreviation": "FLC10",
  "publishDate": "2019-12-14T18:02:42.537Z",
  "placement": 1,
  "downloads": 50,
  "views": 1065,
  "rating": 0,
  "format": {
    "id": 8,
    "name": "Goat",
    "icon": "bluesheep",
    "banlist": "April 2005",
    "videoName": null,
    "videoId": null,
    "videoPlaylistId": null
  },
  "builder": {
    "id": "9SZ3oySHK4WE4wMS67Ucju",
    "name": "thenano5560",
    "discordId": "539827308710854662",
    "discordPfp": null
  },
  "event": {
    "id": 294,
    "isRepresentative": true
  },
  "updatedAt": "2025-11-26T21:43:49.637Z",
  "main": [
    {
      "name": "Black Luster Soldier - Envoy of the Beginning",
      "cleanName": "Black Luster Soldier Envoy of the Beginning",
      "id": 951,
      "artworkId": "72989439",
      "sortPriority": 3
    },
    {
      "name": "Blade Knight",
      "cleanName": "Blade Knight",
      "id": 1035,
      "artworkId": "39507162",
      "sortPriority": 3
    },
    {
      "name": "Breaker the Magical Warrior",
      "cleanName": "Breaker the Magical Warrior",
      "id": 1196,
      "artworkId": "71413901",
      "sortPriority": 3
    },
    {
      "name": "Chaos Sorcerer",
      "cleanName": "Chaos Sorcerer",
      "id": 1494,
      "artworkId": "9596126",
      "sortPriority": 3
    },
    {
      "name": "D.D. Assailant",
      "cleanName": "D D Assailant",
      "id": 2056,
      "artworkId": "70074904",
      "sortPriority": 3
    },
    {
      "name": "D.D. Warrior Lady",
      "cleanName": "D D Warrior Lady",
      "id": 2076,
      "artworkId": "7572887",
      "sortPriority": 3
    },
    {
      "name": "Don Zaloog",
      "cleanName": "Don Zaloog",
      "id": 2721,
      "artworkId": "76922029",
      "sortPriority": 3
    },
    {
      "name": "Exiled Force",
      "cleanName": "Exiled Force",
      "id": 3337,
      "artworkId": "74131780",
      "sortPriority": 3
    },
    {
      "name": "Kycoo the Ghost Destroyer",
      "cleanName": "Kycoo the Ghost Destroyer",
      "id": 5484,
      "artworkId": "88240808",
      "sortPriority": 3
    },
    {
      "name": "Kycoo the Ghost Destroyer",
      "cleanName": "Kycoo the Ghost Destroyer",
      "id": 5484,
      "artworkId": "88240808",
      "sortPriority": 3
    },
    {
      "name": "Sangan",
      "cleanName": "Sangan",
      "id": 8516,
      "artworkId": "26202165",
      "sortPriority": 3
    },
    {
      "name": "Sinister Serpent",
      "cleanName": "Sinister Serpent",
      "id": 8864,
      "artworkId": "8131171",
      "sortPriority": 3
    },
    {
      "name": "Thunder Dragon",
      "cleanName": "Thunder Dragon",
      "id": 10028,
      "artworkId": "31786629",
      "sortPriority": 3
    },
    {
      "name": "Thunder Dragon",
      "cleanName": "Thunder Dragon",
      "id": 10028,
      "artworkId": "31786629",
      "sortPriority": 3
    },
    {
      "name": "Thunder Dragon",
      "cleanName": "Thunder Dragon",
      "id": 10028,
      "artworkId": "31786629",
      "sortPriority": 3
    },
    {
      "name": "Tribe-Infecting Virus",
      "cleanName": "Tribe Infecting Virus",
      "id": 10273,
      "artworkId": "33184167",
      "sortPriority": 3
    },
    {
      "name": "Book of Moon",
      "cleanName": "Book of Moon",
      "id": 1134,
      "artworkId": "14087893",
      "sortPriority": 15
    },
    {
      "name": "Book of Moon",
      "cleanName": "Book of Moon",
      "id": 1134,
      "artworkId": "14087893",
      "sortPriority": 15
    },
    {
      "name": "Delinquent Duo",
      "cleanName": "Delinquent Duo",
      "id": 2421,
      "artworkId": "44763025",
      "sortPriority": 15
    },
    {
      "name": "Graceful Charity",
      "cleanName": "Graceful Charity",
      "id": 4392,
      "artworkId": "79571449",
      "sortPriority": 15
    },
    {
      "name": "Heavy Storm",
      "cleanName": "Heavy Storm",
      "id": 4677,
      "artworkId": "19613556",
      "sortPriority": 15
    },
    {
      "name": "Mystical Space Typhoon",
      "cleanName": "Mystical Space Typhoon",
      "id": 6656,
      "artworkId": "5318639",
      "sortPriority": 15
    },
    {
      "name": "Nobleman of Crossout",
      "cleanName": "Nobleman of Crossout",
      "id": 6902,
      "artworkId": "71044499",
      "sortPriority": 15
    },
    {
      "name": "Nobleman of Crossout",
      "cleanName": "Nobleman of Crossout",
      "id": 6902,
      "artworkId": "71044499",
      "sortPriority": 15
    },
    {
      "name": "Pot of Greed",
      "cleanName": "Pot of Greed",
      "id": 7643,
      "artworkId": "55144522",
      "sortPriority": 15
    },
    {
      "name": "Premature Burial",
      "cleanName": "Premature Burial",
      "id": 7727,
      "artworkId": "70828912",
      "sortPriority": 15
    },
    {
      "name": "Reinforcement of the Army",
      "cleanName": "Reinforcement of the Army",
      "id": 8138,
      "artworkId": "32807846",
      "sortPriority": 15
    },
    {
      "name": "Reinforcement of the Army",
      "cleanName": "Reinforcement of the Army",
      "id": 8138,
      "artworkId": "32807846",
      "sortPriority": 15
    },
    {
      "name": "Snatch Steal",
      "cleanName": "Snatch Steal",
      "id": 8966,
      "artworkId": "45986603",
      "sortPriority": 15
    },
    {
      "name": "Call of the Haunted",
      "cleanName": "Call of the Haunted",
      "id": 1356,
      "artworkId": "97077563",
      "sortPriority": 16
    },
    {
      "name": "Mirror Force",
      "cleanName": "Mirror Force",
      "id": 6464,
      "artworkId": "44095762",
      "sortPriority": 16
    },
    {
      "name": "Phoenix Wing Wind Blast",
      "cleanName": "Phoenix Wing Wind Blast",
      "id": 7543,
      "artworkId": "63356631",
      "sortPriority": 16
    },
    {
      "name": "Phoenix Wing Wind Blast",
      "cleanName": "Phoenix Wing Wind Blast",
      "id": 7543,
      "artworkId": "63356631",
      "sortPriority": 16
    },
    {
      "name": "Ring of Destruction",
      "cleanName": "Ring of Destruction",
      "id": 8264,
      "artworkId": "83555667",
      "sortPriority": 16
    },
    {
      "name": "Solemn Judgment",
      "cleanName": "Solemn Judgment",
      "id": 8991,
      "artworkId": "41420027",
      "sortPriority": 16
    },
    {
      "name": "Solemn Judgment",
      "cleanName": "Solemn Judgment",
      "id": 8991,
      "artworkId": "41420027",
      "sortPriority": 16
    },
    {
      "name": "Solemn Judgment",
      "cleanName": "Solemn Judgment",
      "id": 8991,
      "artworkId": "41420027",
      "sortPriority": 16
    },
    {
      "name": "Torrential Tribute",
      "cleanName": "Torrential Tribute",
      "id": 10167,
      "artworkId": "53582587",
      "sortPriority": 16
    },
    {
      "name": "Trap Dustshoot",
      "cleanName": "Trap Dustshoot",
      "id": 10202,
      "artworkId": "64697231",
      "sortPriority": 16
    },
    {
      "name": "Trap Dustshoot",
      "cleanName": "Trap Dustshoot",
      "id": 10202,
      "artworkId": "64697231",
      "sortPriority": 16
    }
  ],
  "extra": [
    {
      "name": "Dark Balter the Terrible",
      "cleanName": "Dark Balter the Terrible",
      "id": 2191,
      "artworkId": "80071763",
      "sortPriority": 6
    },
    {
      "name": "Dark Balter the Terrible",
      "cleanName": "Dark Balter the Terrible",
      "id": 2191,
      "artworkId": "80071763",
      "sortPriority": 6
    },
    {
      "name": "Dark Balter the Terrible",
      "cleanName": "Dark Balter the Terrible",
      "id": 2191,
      "artworkId": "80071763",
      "sortPriority": 6
    },
    {
      "name": "Dark Blade the Dragon Knight",
      "cleanName": "Dark Blade the Dragon Knight",
      "id": 2196,
      "artworkId": "86805855",
      "sortPriority": 6
    },
    {
      "name": "Dark Blade the Dragon Knight",
      "cleanName": "Dark Blade the Dragon Knight",
      "id": 2196,
      "artworkId": "86805855",
      "sortPriority": 6
    },
    {
      "name": "Dark Blade the Dragon Knight",
      "cleanName": "Dark Blade the Dragon Knight",
      "id": 2196,
      "artworkId": "86805855",
      "sortPriority": 6
    },
    {
      "name": "Gatling Dragon",
      "cleanName": "Gatling Dragon",
      "id": 3957,
      "artworkId": "87751584",
      "sortPriority": 6
    },
    {
      "name": "Gatling Dragon",
      "cleanName": "Gatling Dragon",
      "id": 3957,
      "artworkId": "87751584",
      "sortPriority": 6
    },
    {
      "name": "Gatling Dragon",
      "cleanName": "Gatling Dragon",
      "id": 3957,
      "artworkId": "87751584",
      "sortPriority": 6
    },
    {
      "name": "Thousand Dragon",
      "cleanName": "Thousand Dragon",
      "id": 10009,
      "artworkId": "41462083",
      "sortPriority": 6
    },
    {
      "name": "Thousand Dragon",
      "cleanName": "Thousand Dragon",
      "id": 10009,
      "artworkId": "41462083",
      "sortPriority": 6
    },
    {
      "name": "Thousand Dragon",
      "cleanName": "Thousand Dragon",
      "id": 10009,
      "artworkId": "41462083",
      "sortPriority": 6
    },
    {
      "name": "Thousand-Eyes Restrict",
      "cleanName": "Thousand Eyes Restrict",
      "id": 10015,
      "artworkId": "63519819",
      "sortPriority": 6
    },
    {
      "name": "Thousand-Eyes Restrict",
      "cleanName": "Thousand Eyes Restrict",
      "id": 10015,
      "artworkId": "63519819",
      "sortPriority": 6
    },
    {
      "name": "Thousand-Eyes Restrict",
      "cleanName": "Thousand Eyes Restrict",
      "id": 10015,
      "artworkId": "63519819",
      "sortPriority": 6
    }
  ],
  "side": [
    {
      "name": "Big Shield Gardna",
      "cleanName": "Big Shield Gardna",
      "id": 915,
      "artworkId": "65240384",
      "sortPriority": 3
    },
    {
      "name": "Greenkappa",
      "cleanName": "Greenkappa",
      "id": 4502,
      "artworkId": "61831093",
      "sortPriority": 3
    },
    {
      "name": "Mystic Swordsman LV2",
      "cleanName": "Mystic Swordsman LV2",
      "id": 6639,
      "artworkId": "47507260",
      "sortPriority": 3
    },
    {
      "name": "Zombyra the Dark",
      "cleanName": "Zombyra the Dark",
      "id": 11299,
      "artworkId": "88472456",
      "sortPriority": 3
    },
    {
      "name": "Book of Moon",
      "cleanName": "Book of Moon",
      "id": 1134,
      "artworkId": "14087893",
      "sortPriority": 15
    },
    {
      "name": "Lightning Vortex",
      "cleanName": "Lightning Vortex",
      "id": 5656,
      "artworkId": "69162969",
      "sortPriority": 15
    },
    {
      "name": "Mind Crush",
      "cleanName": "Mind Crush",
      "id": 6421,
      "artworkId": "15800838",
      "sortPriority": 16
    },
    {
      "name": "Mind Crush",
      "cleanName": "Mind Crush",
      "id": 6421,
      "artworkId": "15800838",
      "sortPriority": 16
    },
    {
      "name": "Royal Decree",
      "cleanName": "Royal Decree",
      "id": 8363,
      "artworkId": "51452091",
      "sortPriority": 16
    },
    {
      "name": "Royal Decree",
      "cleanName": "Royal Decree",
      "id": 8363,
      "artworkId": "51452091",
      "sortPriority": 16
    },
    {
      "name": "Royal Decree",
      "cleanName": "Royal Decree",
      "id": 8363,
      "artworkId": "51452091",
      "sortPriority": 16
    },
    {
      "name": "Skill Drain",
      "cleanName": "Skill Drain",
      "id": 8879,
      "artworkId": "82732705",
      "sortPriority": 16
    },
    {
      "name": "Skill Drain",
      "cleanName": "Skill Drain",
      "id": 8879,
      "artworkId": "82732705",
      "sortPriority": 16
    },
    {
      "name": "Skill Drain",
      "cleanName": "Skill Drain",
      "id": 8879,
      "artworkId": "82732705",
      "sortPriority": 16
    },
    {
      "name": "Trap Dustshoot",
      "cleanName": "Trap Dustshoot",
      "id": 10202,
      "artworkId": "64697231",
      "sortPriority": 16
    }
  ]
}